CHANGES.rst
LICENSE.txt
MANIFEST.in
README.rst
setup.py
smartcov.py
pytest_smartcov.egg-info/PKG-INFO
pytest_smartcov.egg-info/SOURCES.txt
pytest_smartcov.egg-info/dependency_links.txt
pytest_smartcov.egg-info/entry_points.txt
pytest_smartcov.egg-info/not-zip-safe
pytest_smartcov.egg-info/requires.txt
pytest_smartcov.egg-info/top_level.txt